test_project_3/__init__.py
test_project_3/_base_client.py
test_project_3/_client.py
test_project_3/_compat.py
test_project_3/_constants.py
test_project_3/_exceptions.py
test_project_3/_files.py
test_project_3/_models.py
test_project_3/_qs.py
test_project_3/_resource.py
test_project_3/_response.py
test_project_3/_streaming.py
test_project_3/_types.py
test_project_3/_version.py
test_project_3/py.typed
test_project_3/_utils/__init__.py
test_project_3/_utils/_compat.py
test_project_3/_utils/_datetime_parse.py
test_project_3/_utils/_logs.py
test_project_3/_utils/_proxy.py
test_project_3/_utils/_reflection.py
test_project_3/_utils/_resources_proxy.py
test_project_3/_utils/_streams.py
test_project_3/_utils/_sync.py
test_project_3/_utils/_transform.py
test_project_3/_utils/_typing.py
test_project_3/_utils/_utils.py
test_project_3/lib/.keep
test_project_3/resources/__init__.py
test_project_3/resources/pets.py
test_project_3/resources/users.py
test_project_3/resources/store/__init__.py
test_project_3/resources/store/orders.py
test_project_3/resources/store/store.py
test_project_3/types/__init__.py
test_project_3/types/category.py
test_project_3/types/category_param.py
test_project_3/types/pet.py
test_project_3/types/pet_create_params.py
test_project_3/types/pet_find_by_status_params.py
test_project_3/types/pet_find_by_status_response.py
test_project_3/types/pet_find_by_tags_params.py
test_project_3/types/pet_find_by_tags_response.py
test_project_3/types/pet_update_by_id_params.py
test_project_3/types/pet_update_params.py
test_project_3/types/pet_upload_image_params.py
test_project_3/types/pet_upload_image_response.py
test_project_3/types/store_list_inventory_response.py
test_project_3/types/user.py
test_project_3/types/user_create_params.py
test_project_3/types/user_create_with_list_params.py
test_project_3/types/user_login_params.py
test_project_3/types/user_login_response.py
test_project_3/types/user_param.py
test_project_3/types/user_update_params.py
test_project_3-0.0.2.dist-info/METADATA
test_project_3-0.0.2.dist-info/WHEEL
test_project_3-0.0.2.dist-info/licenses/LICENSE
test_project_3-0.0.2.dist-info/RECORD
